noxii/Test.py
noxii/__init__.py
noxii/__main__.py
noxii/api.py
noxii/cli.py
noxii/errors.py
noxii/models.py
noxii-0.2.2.dist-info/LICENSE
noxii-0.2.2.dist-info/METADATA
noxii-0.2.2.dist-info/WHEEL
noxii-0.2.2.dist-info/top_level.txt
noxii-0.2.2.dist-info/RECORD
